{
  "folder": "mV306wqqkeIDd9EE",
  "name": "Small Dagger",
  "type": "weapon",
  "_id": "wKklDxs5nkzILNp4",
  "img": "icons/weapons/daggers/dagger-straight-cracked.webp",
  "system": {
    "description": "",
    "actions": {},
    "attached": [],
    "tier": 1,
    "equipped": false,
    "secondary": true,
    "burden": "oneHanded",
    "weaponFeatures": [
      {
        "value": "paired",
        "effectIds": [
          "HKh73AHxImdgxgTg"
        ],
        "actionIds": []
      }
    ],
    "attack": {
      "name": "Attack",
      "img": "icons/skills/melee/blood-slash-foam-red.webp",
      "_id": "AVjlF2Mv5AMDflgy",
      "systemPath": "attack",
      "type": "attack",
      "range": "melee",
      "target": {
        "type": "any",
        "amount": 1
      },
      "roll": {
        "trait": "finesse",
        "type": "attack",
        "difficulty": null,
        "bonus": null,
        "advState": "neutral",
        "diceRolling": {
          "multiplier": "prof",
          "flatMultiplier": 1,
          "dice": "d6",
          "compare": null,
          "treshold": null
        },
        "useDefault": false
      },
      "damage": {
        "parts": [
          {
            "type": [
              "physical"
            ],
            "value": {
              "multiplier": "prof",
              "dice": "d8",
              "flatMultiplier": 1,
              "bonus": null,
              "custom": {
                "enabled": false
              }
            },
            "applyTo": "hitPoints",
            "resultBased": false,
            "valueAlt": {
              "multiplier": "prof",
              "flatMultiplier": 1,
              "dice": "d6",
              "bonus": null,
              "custom": {
                "enabled": false
              }
            },
            "base": false
          }
        ],
        "includeBase": false
      },
      "description": "",
      "chatDisplay": true,
      "actionType": "action",
      "cost": [],
      "uses": {
        "value": null,
        "max": null,
        "recovery": null
      },
      "effects": [],
      "save": {
        "trait": null,
        "difficulty": null,
        "damageMod": "none"
      }
    },
    "rules": {
      "attack": {
        "roll": {
          "trait": null
        }
      }
    }
  },
  "effects": [
    {
      "name": "Paired",
      "description": "Add this Secondary Weapon's tier + 1 to your primary weapon against targets within Melee range",
      "img": "icons/skills/melee/weapons-crossed-swords-yellow-teal.webp",
      "changes": [
        {
          "key": "system.bonuses.damage.primaryWeapon.bonus",
          "mode": 2,
          "value": "ITEM.@system.tier + 1"
        }
      ],
      "system": {
        "rangeDependence": {
          "enabled": true,
          "range": "melee",
          "target": "hostile",
          "type": "withinRange"
        }
      },
      "_id": "HKh73AHxImdgxgTg",
      "type": "base",
      "disabled": false,
      "duration": {
        "startTime": null,
        "combat": null
      },
      "origin": null,
      "tint": "#ffffff",
      "transfer": true,
      "statuses": [],
      "sort": 0,
      "flags": {},
      "_stats": {
        "compendiumSource": null,
        "duplicateSource": null,
        "exportSource": null,
        "coreVersion": "13.347",
        "systemId": "daggerheart",
        "systemVersion": "1.0.4",
        "createdTime": 1755268300195,
        "modifiedTime": 1755268300195,
        "lastModifiedBy": "VZIeX2YDvX338Zvr"
      },
      "_key": "!items.effects!wKklDxs5nkzILNp4.HKh73AHxImdgxgTg"
    }
  ],
  "sort": 0,
  "ownership": {
    "default": 0,
    "FecEtPuoQh6MpjQ0": 3
  },
  "flags": {},
  "_stats": {
    "compendiumSource": null,
    "duplicateSource": null,
    "exportSource": null,
    "coreVersion": "13.347",
    "systemId": "daggerheart",
    "systemVersion": "1.0.4",
    "createdTime": 1753744141625,
    "modifiedTime": 1755268300204,
    "lastModifiedBy": "VZIeX2YDvX338Zvr"
  },
  "_key": "!items!wKklDxs5nkzILNp4"
}
