{
  "name": "Acidpaste",
  "type": "consumable",
  "_id": "cfVFmS8vT9dbq9s1",
  "img": "icons/commodities/materials/bowl-powder-teal.webp",
  "system": {
    "description": "<p>This paste eats away walls and other surfaces in bright flashes.</p>",
    "quantity": 1,
    "actions": {
      "FQ2Ty0pP3z6JrBr6": {
        "type": "effect",
        "_id": "FQ2Ty0pP3z6JrBr6",
        "systemPath": "actions",
        "description": "<p>This paste eats away walls and other surfaces in bright flashes.</p>",
        "chatDisplay": true,
        "actionType": "action",
        "cost": [],
        "uses": {
          "value": null,
          "max": "",
          "recovery": null
        },
        "effects": [],
        "target": {
          "type": "any",
          "amount": null
        },
        "name": "Use",
        "img": "icons/commodities/materials/bowl-powder-teal.webp",
        "range": ""
      }
    },
    "consumeOnUse": true,
    "attribution": {
      "source": "Daggerheart SRD",
      "page": 61,
      "artist": ""
    }
  },
  "effects": [],
  "folder": null,
  "sort": 0,
  "ownership": {
    "default": 0,
    "OFxauskoxcvVTVNA": 3
  },
  "flags": {},
  "_stats": {
    "compendiumSource": null,
    "duplicateSource": null,
    "exportSource": null,
    "coreVersion": "13.347",
    "systemId": "daggerheart",
    "systemVersion": "1.0.5",
    "createdTime": 1753590344700,
    "modifiedTime": 1755432861888,
    "lastModifiedBy": "VZIeX2YDvX338Zvr"
  },
  "_key": "!items!cfVFmS8vT9dbq9s1"
}
